{"abandoned": 624, "abandoned_30": 23, "abandoned_365": 400, "abandoned_7": 7, "closed": 2385, "closed_30": 126, "closed_365": 2054, "closed_7": 18, "diff_netabandoned_30": 7, "diff_netabandoned_365": 254, "diff_netabandoned_7": -1, "diff_netclosed_30": -64, "diff_netclosed_365": 1805, "diff_netclosed_7": -34, "diff_netmerged_30": -71, "diff_netmerged_365": 1551, "diff_netmerged_7": -33, "diff_netpending_30": 32, "diff_netpending_365": 244, "diff_netpending_7": -5, "diff_netsubmitted_30": -32, "diff_netsubmitted_365": 2049, "diff_netsubmitted_7": -39, "diff_netsubmitters_30": -1, "diff_netsubmitters_365": 32, "diff_netsubmitters_7": -1, "first_date": "2011-10-26", "inprogress": 0, "last_date": "2014-10-11", "merged": 1761, "merged_30": 103, "merged_365": 1654, "merged_7": 11, "new": 218, "opened": 218, "pending": 273, "pending_30": 85, "pending_365": 257, "pending_7": 27, "percentage_abandoned_30": 43, "percentage_abandoned_365": 173, "percentage_abandoned_7": 12, "percentage_closed_30": 33, "percentage_closed_365": 724, "percentage_closed_7": 65, "percentage_merged_30": 40, "percentage_merged_365": 1505, "percentage_merged_7": 75, "percentage_pending_30": 60, "percentage_pending_365": 1876, "percentage_pending_7": 15, "percentage_submitted_30": 13, "percentage_submitted_365": 782, "percentage_submitted_7": 46, "percentage_submitters_30": 3, "percentage_submitters_365": 65, "percentage_submitters_7": 5, "repositories": 34, "review_time_days_avg": 16.94950844277676, "review_time_days_median": 2.8852, "reviewers": 140, "submitted": 2658, "submitted_30": 211, "submitted_365": 2311, "submitted_7": 45, "submitters": 100, "submitters_30": 26, "submitters_365": 81, "submitters_7": 16}