{"senders.": {"id": [12, 39, 2, 41513, 196, 41, 40, 321, 1, 217], "senders": ["Fabian Deutsch", "Michael Burns", "Gerrit Code Review", "jenkins@ovirt.org", "Joey Boggs", "Ryan Barry", "Douglas Schilling Landgraf", "hadong", "Itamar Heim", "Wenyi Gao"], "sent": [3800, 3283, 2884, 1727, 946, 532, 349, 236, 61, 40]}, "senders.last month": {"id": [12, 2, 40, 41, 41513, 321, 60], "senders": ["Fabian Deutsch", "Gerrit Code Review", "Douglas Schilling Landgraf", "Ryan Barry", "jenkins@ovirt.org", "hadong", "Doron Fediuck"], "sent": [119, 42, 38, 33, 26, 2, 1]}, "senders.last year": {"id": [12, 2, 40, 41, 41513, 321, 196, 1, 11, 9], "senders": ["Fabian Deutsch", "Gerrit Code Review", "Douglas Schilling Landgraf", "Ryan Barry", "jenkins@ovirt.org", "hadong", "Joey Boggs", "Itamar Heim", "Antoni S. Puimedon", "David Caro"], "sent": [1433, 1286, 335, 318, 151, 91, 78, 59, 19, 9]}}