{"senders.": {"id": [1, 40094, 8, 35, 28, 40347, 39, 60, 41583, 133], "senders": ["Itamar Heim", "gianluca.cecchi", "Sandro Bonazzola", "Alon Bar-Lev", "Dan Kenigsberg", "s.kieske", "Michael Burns", "Doron Fediuck", "Karli.Sjoberg@slu.se", "Michal Skrivanek"], "sent": [2057, 783, 762, 626, 615, 607, 515, 437, 301, 279]}, "senders.last month": {"id": [8, 35, 40094, 42514, 41477, 42506, 1, 41527, 28, 46], "senders": ["Sandro Bonazzola", "Alon Bar-Lev", "gianluca.cecchi", "Cong_Yue@alliedtelesis.com", "hypunit@gmail.com", "automatikdonn", "Itamar Heim", "jj197005@gmail.com", "Dan Kenigsberg", "Yedidyah Bar David"], "sent": [39, 33, 32, 31, 28, 22, 18, 18, 17, 17]}, "senders.last year": {"id": [1, 8, 40347, 40094, 40600, 35, 28, 60, 46, 39707], "senders": ["Itamar Heim", "Sandro Bonazzola", "s.kieske", "gianluca.cecchi", "midnightsteel", "Alon Bar-Lev", "Dan Kenigsberg", "Doron Fediuck", "Yedidyah Bar David", "dron"], "sent": [633, 605, 504, 290, 274, 259, 252, 229, 207, 189]}}