{"senders.": {"id": [97, 39294, 1, 80, 85, 39256, 43, 13, 72, 17], "senders": ["Allon Mureinik", "sbonazzo@redhat.com", "Itamar Heim", "Yair Zaslavsky", "Tal Nisan", "oourfali@redhat.com", "Yaniv Dary", "Michael Pasternak", "Daniel Erez", "Juan Hernandez"], "sent": [1070, 1029, 996, 971, 919, 847, 831, 806, 787, 736]}, "senders.last month": {"id": [85, 39256, 39294, 17, 80, 124, 43, 72, 121, 87], "senders": ["Tal Nisan", "oourfali@redhat.com", "sbonazzo@redhat.com", "Juan Hernandez", "Yair Zaslavsky", "Lior Vernia", "Yaniv Dary", "Daniel Erez", "awels", "Omer Frenkel"], "sent": [308, 105, 92, 64, 34, 31, 29, 22, 20, 19]}, "senders.last year": {"id": [1, 39294, 85, 39256, 43, 17, 97, 56, 80, 72], "senders": ["Itamar Heim", "sbonazzo@redhat.com", "Tal Nisan", "oourfali@redhat.com", "Yaniv Dary", "Juan Hernandez", "Allon Mureinik", "Eli Mesika", "Yair Zaslavsky", "Daniel Erez"], "sent": [981, 894, 710, 674, 622, 406, 373, 368, 358, 303]}}