{"senders.": {"id": [41513, 41649, 10, 41610, 1, 41675, 9, 6, 41968, 8], "senders": ["jenkins@ovirt.org", "logwatch@lists.ovirt.org", "Eyal Edri", "kwade@redhat.com", "Itamar Heim", "MAILER-DAEMON@lists.ovirt.org", "David Caro", "Ewoud Kohl van Wijngaarden", "trac@fedorahosted.org", "Sandro Bonazzola"], "sent": [2466, 869, 740, 511, 445, 429, 363, 306, 286, 270]}, "senders.last month": {"id": [41513, 41649, 8, 35, 9, 17, 61, 42334, 89, 6], "senders": ["jenkins@ovirt.org", "logwatch@lists.ovirt.org", "Sandro Bonazzola", "Alon Bar-Lev", "David Caro", "Juan Hernandez", "Nir Soffer", "aaviram@redhat.com", "Einav Cohen", "Ewoud Kohl van Wijngaarden"], "sent": [58, 30, 8, 5, 5, 2, 2, 1, 1, 1]}, "senders.last year": {"id": [41513, 41649, 9, 8, 10, 41968, 35, 41675, 41859, 41732], "senders": ["jenkins@ovirt.org", "logwatch@lists.ovirt.org", "David Caro", "Sandro Bonazzola", "Eyal Edri", "trac@fedorahosted.org", "Alon Bar-Lev", "MAILER-DAEMON@lists.ovirt.org", "root@lists.ovirt.org", "mscherer@redhat.com"], "sent": [1943, 347, 260, 217, 172, 151, 77, 63, 53, 51]}}