{"actions": 4736, "added_lines": 78156.0, "added_lines_30": 113789, "added_lines_365": 2227869, "added_lines_7": 22718, "authors": 21, "authors_30": 3, "authors_365": 10, "authors_7": 3, "avg_commits_author": 61.2381, "avg_commits_month": 38.9697, "avg_files_author": 106.381, "avg_files_month": 67.697, "branches": 17, "commits": 1286, "commits_30": 43, "commits_365": 302, "commits_7": 14, "committers": 10, "diff_netadded_lines_30": -5814, "diff_netadded_lines_365": 652797, "diff_netadded_lines_7": -12600, "diff_netauthors_30": 1, "diff_netauthors_365": -6, "diff_netauthors_7": 1, "diff_netcommits_30": 19, "diff_netcommits_365": -237, "diff_netcommits_7": -2, "diff_netfiles_30": -55, "diff_netfiles_365": -675, "diff_netfiles_7": -5, "diff_netremoved_lines_30": -18033, "diff_netremoved_lines_365": 353271, "diff_netremoved_lines_7": -13801, "files": 2234, "files_30": 77, "files_365": 697, "files_7": 20, "first_date": "2011-11-01", "last_date": "2014-09-09", "percentage_added_lines_30": 4, "percentage_added_lines_365": 41, "percentage_added_lines_7": 35, "percentage_authors_30": 50, "percentage_authors_365": 37, "percentage_authors_7": 50, "percentage_commits_30": 79, "percentage_commits_365": 43, "percentage_commits_7": 12, "percentage_files_30": 41, "percentage_files_365": 49, "percentage_files_7": 19, "percentage_removed_lines_30": 28, "percentage_removed_lines_365": 31, "percentage_removed_lines_7": 63, "removed_lines": 41636.0, "removed_lines_30": 44803, "removed_lines_365": 1467267, "removed_lines_7": 7832, "repositories": 11}