{"authors.": {"authors": ["David Caro", "Ewoud Kohl van Wijngaarden", "Kiril Nesenko", "Ohad Basan", "Eyal Edri", "Sandro Bonazzola", "Fabian Deutsch", "Paz Dangur", "quaid"], "commits": [48, 28, 14, 8, 6, 2, 1, 1, 1], "id": [9, 6, 7, 5, 10, 8, 12, 263, 262]}, "authors.last month": {"authors": "Sandro Bonazzola", "commits": 1, "id": 8}, "authors.last year": {"authors": ["David Caro", "Ewoud Kohl van Wijngaarden", "Kiril Nesenko", "Ohad Basan", "Eyal Edri", "Sandro Bonazzola", "Fabian Deutsch", "Paz Dangur"], "commits": [46, 15, 8, 8, 6, 2, 1, 1], "id": [9, 6, 7, 5, 10, 8, 12, 263]}}