{"senders.": {"id": [42104, 42313, 42149, 42157, 42237, 42266, 42087, 42283, 42134, 42096], "senders": [" apuimedo", "@danken", " evilissimo", " fromani", " nsoffer", " saggi", " aglitke", " tdfkaSaggi", " deepakcs", " amuller"], "sent": [10989, 5657, 2657, 2439, 2433, 2122, 2079, 1531, 1337, 1212]}, "senders.last month": {"id": [42104, 42313, 42237, 42157, 42253, 42152, 42141, 42243, 42149, 42095], "senders": [" apuimedo", "@danken", " nsoffer", " fromani", " pkliczew", " fabiand", " dougsland", " osvoboda", " evilissimo", " alitke__"], "sent": [801, 372, 350, 247, 236, 225, 112, 99, 94, 90]}, "senders.last year": {"id": [42104, 42313, 42157, 42237, 42149, 42303, 42243, 42152, 42124, 42096], "senders": [" apuimedo", "@danken", " fromani", " nsoffer", " evilissimo", " ybronhei", " osvoboda", " fabiand", " celebdor", " amuller"], "sent": [7946, 3554, 2439, 2428, 1766, 882, 812, 677, 660, 580]}}