{"senders.":{"id":[82,30,64,10,42,54,31,71,14,1,34,55,63,61,58,8,59,69,56,11,46,33,70,93,37,110,44,75,38,104],"senders":["Allon Mureinik","Alon Bar-Lev","Yair Zaslavsky","Michael Pasternak","Moti Asayag","Daniel Erez","Sandro Bonazzola","Omer Frenkel","Juan Hernandez","Itamar Heim","Mike Burns","Gilad Chaplik","Eli Mesika","Michael Kublin","Mike Kolesnik","Fabian Deutsch","Roy Golan","Tal Nisan","Vojtech Szocs","Ofer Schreiber","Doron Fediuck","Oved Ourfali","Tomas Jelinek","Liron Aravot","Yaniv Dary","Lior Vernia","Laszlo Hornyak","Alona Kaplan","Alex Lourie","Arik Hadas"],"sent":[11195,7815,6913,5132,4418,4272,4263,4135,4124,4095,4081,3958,3846,3264,3218,2699,2544,2357,2233,2210,2102,1883,1833,1682,1548,1546,1529,1505,1452,1370]},"senders.last year":{"id":[82,30,31,64,1,10,71,14,54,8,63,42,69,55,110,34,70,11,56,59,104,44,39,106,58,93,18,37,46,33],"senders":["Allon Mureinik","Alon Bar-Lev","Sandro Bonazzola","Yair Zaslavsky","Itamar Heim","Michael Pasternak","Omer Frenkel","Juan Hernandez","Daniel Erez","Fabian Deutsch","Eli Mesika","Moti Asayag","Tal Nisan","Gilad Chaplik","Lior Vernia","Mike Burns","Tomas Jelinek","Ofer Schreiber","Vojtech Szocs","Roy Golan","Arik Hadas","Laszlo Hornyak","Yedidyah Bar David","Alissa Bonas","Mike Kolesnik","Liron Aravot","Ravi Nori","Yaniv Dary","Doron Fediuck","Oved Ourfali"],"sent":[6280,6094,4250,3265,2459,2281,2260,2232,2121,1940,1896,1863,1783,1769,1539,1425,1350,1287,1234,1154,1151,1132,1078,1053,1035,1025,1003,904,851,849]},"senders.last month":{"id":[31,30,14,1,42,82,110,37,54,64,58,55,71,39,59,119,63,69,129,33,56,46,70,125,104,28,13,35,106,103],"senders":["Sandro Bonazzola","Alon Bar-Lev","Juan Hernandez","Itamar Heim","Moti Asayag","Allon Mureinik","Lior Vernia","Yaniv Dary","Daniel Erez","Yair Zaslavsky","Mike Kolesnik","Gilad Chaplik","Omer Frenkel","Yedidyah Bar David","Roy Golan","Martin Perina","Eli Mesika","Tal Nisan","Sergey Gotliv","Oved Ourfali","Vojtech Szocs","Doron Fediuck","Tomas Jelinek","Mooli Tayer","Arik Hadas","Martin Betak","Adam Litke","Douglas Schilling Landgraf","Alissa Bonas","Frantisek Kobzik"],"sent":[568,505,395,360,282,256,238,227,185,183,181,178,153,135,127,123,122,122,93,93,91,82,80,79,78,73,72,59,57,55]}}