{"senders.":{"id":[82,30,64,10,42,31,54,1,14,71,34,55,63,61,58,8,59,69,56,11,46,33,70,93,37,110,44,75,38,104],"senders":["Allon Mureinik","Alon Bar-Lev","Yair Zaslavsky","Michael Pasternak","Moti Asayag","Sandro Bonazzola","Daniel Erez","Itamar Heim","Juan Hernandez","Omer Frenkel","Mike Burns","Gilad Chaplik","Eli Mesika","Michael Kublin","Mike Kolesnik","Fabian Deutsch","Roy Golan","Tal Nisan","Vojtech Szocs","Ofer Schreiber","Doron Fediuck","Oved Ourfali","Tomas Jelinek","Liron Aravot","Yaniv Dary","Lior Vernia","Laszlo Hornyak","Alona Kaplan","Alex Lourie","Arik Hadas"],"sent":[11227,7962,6974,5132,4424,4402,4334,4236,4232,4190,4081,3963,3920,3264,3220,2768,2560,2374,2238,2236,2107,1883,1854,1709,1609,1593,1529,1505,1452,1410]},"senders.last year":{"id":[82,30,31,64,1,71,14,10,54,8,63,42,69,55,110,34,70,11,56,104,59,39,44,93,106,58,18,37,46,33],"senders":["Allon Mureinik","Alon Bar-Lev","Sandro Bonazzola","Yair Zaslavsky","Itamar Heim","Omer Frenkel","Juan Hernandez","Michael Pasternak","Daniel Erez","Fabian Deutsch","Eli Mesika","Moti Asayag","Tal Nisan","Gilad Chaplik","Lior Vernia","Mike Burns","Tomas Jelinek","Ofer Schreiber","Vojtech Szocs","Arik Hadas","Roy Golan","Yedidyah Bar David","Laszlo Hornyak","Liron Aravot","Alissa Bonas","Mike Kolesnik","Ravi Nori","Yaniv Dary","Doron Fediuck","Oved Ourfali"],"sent":[6176,6106,4374,3279,2593,2281,2248,2224,2139,1988,1942,1854,1772,1733,1556,1383,1356,1313,1237,1166,1159,1130,1121,1029,1028,1003,1000,965,849,839]},"senders.last month":{"id":[31,30,14,1,37,42,82,110,64,54,71,63,39,58,55,119,69,59,104,8,70,129,56,28,46,13,125,33,93,120],"senders":["Sandro Bonazzola","Alon Bar-Lev","Juan Hernandez","Itamar Heim","Yaniv Dary","Moti Asayag","Allon Mureinik","Lior Vernia","Yair Zaslavsky","Daniel Erez","Omer Frenkel","Eli Mesika","Yedidyah Bar David","Mike Kolesnik","Gilad Chaplik","Martin Perina","Tal Nisan","Roy Golan","Arik Hadas","Fabian Deutsch","Tomas Jelinek","Sergey Gotliv","Vojtech Szocs","Martin Betak","Doron Fediuck","Adam Litke","Mooli Tayer","Oved Ourfali","Liron Aravot","Michal Skrivanek"],"sent":[703,631,499,496,279,277,276,263,236,224,208,186,177,169,165,151,135,133,117,102,101,98,96,89,87,83,80,71,64,62]}}