{"senders.": {"id": [34, 1, 8, 10, 30, 64, 82, 31, 161, 63], "senders": ["Mike Burns", "Itamar Heim", "Fabian Deutsch", "Michael Pasternak", "Alon Bar-Lev", "Yair Zaslavsky", "Allon Mureinik", "Sandro Bonazzola", "Joey Boggs", "Eli Mesika"], "sent": [4042, 3671, 2994, 1250, 1221, 1143, 1082, 1024, 950, 921]}, "senders.last month": {"id": [1, 8, 31, 63, 37, 14, 30, 64, 42, 56], "senders": ["Itamar Heim", "Fabian Deutsch", "Sandro Bonazzola", "Eli Mesika", "Yaniv Dary", "Juan Hernandez", "Alon Bar-Lev", "Yair Zaslavsky", "Moti Asayag", "Vojtech Szocs"], "sent": [354, 231, 210, 115, 83, 69, 69, 54, 44, 38]}, "senders.last year": {"id": [1, 8, 31, 34, 30, 82, 64, 63, 10, 11], "senders": ["Itamar Heim", "Fabian Deutsch", "Sandro Bonazzola", "Mike Burns", "Alon Bar-Lev", "Allon Mureinik", "Yair Zaslavsky", "Eli Mesika", "Michael Pasternak", "Ofer Schreiber"], "sent": [2134, 1978, 1014, 979, 795, 717, 558, 550, 545, 472]}}