{"senders.":{"id":[82,30,64,10,34,42,54,71,55,1,14,63,31,61,58,8,59,69,11,56,46,33,70,93,44,75,38,37,110,104],"senders":["Allon Mureinik","Alon Bar-Lev","Yair Zaslavsky","Michael Pasternak","Mike Burns","Moti Asayag","Daniel Erez","Omer Frenkel","Gilad Chaplik","Itamar Heim","Juan Hernandez","Eli Mesika","Sandro Bonazzola","Michael Kublin","Mike Kolesnik","Fabian Deutsch","Roy Golan","Tal Nisan","Ofer Schreiber","Vojtech Szocs","Doron Fediuck","Oved Ourfali","Tomas Jelinek","Liron Aravot","Laszlo Hornyak","Alona Kaplan","Alex Lourie","Yaniv Dary","Lior Vernia","Arik Hadas"],"sent":[10919,7289,6715,5113,4079,4068,4058,3960,3756,3721,3713,3686,3642,3264,2995,2666,2404,2224,2200,2142,2007,1771,1753,1631,1529,1505,1452,1293,1280,1251]},"senders.last year":{"id":[82,30,31,64,10,71,1,54,14,63,8,42,34,69,55,11,70,110,58,56,44,93,104,59,106,18,75,39,46,38],"senders":["Allon Mureinik","Alon Bar-Lev","Sandro Bonazzola","Yair Zaslavsky","Michael Pasternak","Omer Frenkel","Itamar Heim","Daniel Erez","Juan Hernandez","Eli Mesika","Fabian Deutsch","Moti Asayag","Mike Burns","Tal Nisan","Gilad Chaplik","Ofer Schreiber","Tomas Jelinek","Lior Vernia","Mike Kolesnik","Vojtech Szocs","Laszlo Hornyak","Liron Aravot","Arik Hadas","Roy Golan","Alissa Bonas","Ravi Nori","Alona Kaplan","Yedidyah Bar David","Doron Fediuck","Alex Lourie"],"sent":[6339,5967,3642,3419,2575,2288,2199,2107,2078,1995,1963,1901,1833,1818,1808,1341,1335,1280,1197,1189,1180,1168,1150,1125,1092,1013,917,911,847,771]},"senders.last month":{"id":[82,31,30,1,71,63,69,106,39,37,55,110,64,33,42,59,54,14,93,112,70,10,56,104,129,122,135,8,41,18],"senders":["Allon Mureinik","Sandro Bonazzola","Alon Bar-Lev","Itamar Heim","Omer Frenkel","Eli Mesika","Tal Nisan","Alissa Bonas","Yedidyah Bar David","Yaniv Dary","Gilad Chaplik","Lior Vernia","Yair Zaslavsky","Oved Ourfali","Moti Asayag","Roy Golan","Daniel Erez","Juan Hernandez","Liron Aravot","Sahina Bose","Tomas Jelinek","Michael Pasternak","Vojtech Szocs","Arik Hadas","Sergey Gotliv","Shubhendu Tripathi","Anmol Babu","Fabian Deutsch","Martin Sivak","Ravi Nori"],"sent":[732,477,392,307,239,222,215,205,179,173,161,150,148,146,142,139,134,131,120,115,114,107,107,103,99,81,79,76,73,72]}}