{"companies": 3, "diff_netsenders_30": 19, "diff_netsenders_365": 105, "diff_netsenders_7": 11, "diff_netsent_30": 1003, "diff_netsent_365": 9561, "diff_netsent_7": -6, "first_date": "2011-11-01", "last_date": "2014-02-16", "percentage_senders_30": 10, "percentage_senders_365": 21, "percentage_senders_7": 11, "percentage_sent_30": 47, "percentage_sent_365": 46, "percentage_sent_7": 0, "repositories": 13, "senders": 942, "senders_14": 142, "senders_180": 423, "senders_30": 205, "senders_365": 605, "senders_60": 264, "senders_7": 112, "senders_730": 890, "senders_90": 297, "senders_init": 725, "senders_response": 763, "sent": 52890, "sent_14": 1398, "sent_180": 14693, "sent_30": 3236, "sent_365": 30026, "sent_60": 5408, "sent_7": 756, "sent_730": 50425, "sent_90": 7809, "sent_response": 44488, "threads": 35834}