{"first_date":"2011-11-01","last_date":"2013-12-22","sent":173188,"senders":920,"repositories":14,"threads":40186,"url":"http://lists.ovirt.org/pipermail/announce/","sent_response":147675,"sent_init":25512,"sent_responses":147667,"sent_no_response":-14674,"thread_size_avg":3.6748,"thread_persons_avg":1.8157,"senders_init":717,"senders_response":751,"companies":5,"sent_7":2545,"senders_7":123,"sent_14":5522,"senders_14":149,"sent_30":11847,"senders_30":186,"sent_60":24145,"senders_60":256,"sent_90":34600,"senders_90":304,"sent_180":66669,"senders_180":410,"sent_365":111851,"senders_365":619,"sent_730":170293,"senders_730":890,"diff_netsent_7":-577,"percentage_sent_7":20,"diff_netsent_30":-453,"percentage_sent_30":3,"diff_netsent_365":53364,"percentage_sent_365":91,"diff_netsenders_7":-8,"percentage_senders_7":6,"diff_netsenders_30":-23,"percentage_senders_30":11,"diff_netsenders_365":122,"percentage_senders_365":24}