{"authors.": {"authors": ["Allon Mureinik", "Alon Bar-Lev", "Daniel Erez", "Moti Asayag", "Gilad Chaplik", "Eli Mesika", "Yair Zaslavsky", "Lior Vernia", "Arik Hadas", "Mike Kolesnik"], "commits": [1364, 1077, 820, 713, 632, 630, 568, 563, 483, 474], "id": [97, 35, 72, 54, 73, 56, 80, 124, 118, 75]}, "authors.last month": {"authors": ["Martin Perina", "Tal Nisan", "Daniel Erez", "Vitor de Lima", "Gilad Chaplik", "Arik Hadas", "Maor Lipchuk", "Vered Volansky", "Juan Hernandez", "Alon Bar-Lev"], "commits": [41, 29, 24, 23, 21, 20, 19, 19, 18, 16], "id": [42, 85, 72, 160, 73, 118, 65, 116, 17, 35]}, "authors.last year": {"authors": ["Alon Bar-Lev", "Lior Vernia", "Daniel Erez", "Yair Zaslavsky", "Arik Hadas", "Allon Mureinik", "Martin Perina", "Moti Asayag", "Ravi Nori", "Tal Nisan"], "commits": [448, 341, 330, 265, 264, 256, 235, 234, 231, 226], "id": [35, 124, 72, 80, 118, 97, 42, 54, 21, 85]}}