{"actions": 97089, "added_lines": 1765476.0, "added_lines_30": 42715, "added_lines_365": 2448271, "added_lines_7": 17147, "authors": 145, "authors_30": 43, "authors_365": 93, "authors_7": 24, "avg_commits_author": 124.0759, "avg_commits_month": 486.2432, "avg_files_author": 123.4483, "avg_files_month": 483.7838, "branches": 16, "commits": 17991, "commits_30": 408, "commits_365": 6439, "commits_7": 96, "committers": 106, "diff_netadded_lines_30": 10373, "diff_netadded_lines_365": 930863, "diff_netadded_lines_7": 8854, "diff_netauthors_30": -4, "diff_netauthors_365": -2, "diff_netauthors_7": -7, "diff_netcommits_30": 3, "diff_netcommits_365": -85, "diff_netcommits_7": -4, "diff_netfiles_30": 89, "diff_netfiles_365": 2913, "diff_netfiles_7": 378, "diff_netremoved_lines_30": 94875, "diff_netremoved_lines_365": 699262, "diff_netremoved_lines_7": 10240, "files": 17900, "files_30": 1398, "files_365": 10816, "files_7": 660, "first_date": "2011-11-01", "last_date": "2014-12-07", "percentage_added_lines_30": 32, "percentage_added_lines_365": 61, "percentage_added_lines_7": 106, "percentage_authors_30": 8, "percentage_authors_365": 2, "percentage_authors_7": 22, "percentage_commits_30": 0, "percentage_commits_365": 1, "percentage_commits_7": 4, "percentage_files_30": 6, "percentage_files_365": 36, "percentage_files_7": 134, "percentage_removed_lines_30": 650, "percentage_removed_lines_365": 63, "percentage_removed_lines_7": 375, "removed_lines": 1155574.0, "removed_lines_30": 109451, "removed_lines_365": 1796627, "removed_lines_7": 12965, "repositories": 1}