{"abandoned": 1755, "abandoned_30": 39, "abandoned_365": 1077, "abandoned_7": 9, "closed": 16939, "closed_30": 836, "closed_365": 11205, "closed_7": 161, "diff_netabandoned_30": -21, "diff_netabandoned_365": 488, "diff_netabandoned_7": -3, "diff_netclosed_30": -225, "diff_netclosed_365": 6559, "diff_netclosed_7": 27, "diff_netmerged_30": -204, "diff_netmerged_365": 6071, "diff_netmerged_7": 30, "diff_netpending_30": 164, "diff_netpending_365": 623, "diff_netpending_7": 55, "diff_netsubmitted_30": -61, "diff_netsubmitted_365": 7182, "diff_netsubmitted_7": 82, "diff_netsubmitters_30": -4, "diff_netsubmitters_365": 8, "diff_netsubmitters_7": -5, "first_date": "2011-10-26", "inprogress": 0, "last_date": "2014-09-27", "merged": 15184, "merged_30": 797, "merged_365": 10128, "merged_7": 152, "new": 494, "opened": 494, "pending": 661, "pending_30": 235, "pending_365": 641, "pending_7": 94, "percentage_abandoned_30": 35, "percentage_abandoned_365": 82, "percentage_abandoned_7": 25, "percentage_closed_30": 21, "percentage_closed_365": 141, "percentage_closed_7": 20, "percentage_merged_30": 20, "percentage_merged_365": 149, "percentage_merged_7": 24, "percentage_pending_30": 230, "percentage_pending_365": 3461, "percentage_pending_7": 141, "percentage_submitted_30": 5, "percentage_submitted_365": 153, "percentage_submitted_7": 47, "percentage_submitters_30": 6, "percentage_submitters_365": 9, "percentage_submitters_7": 11, "repositories": 34, "review_time_days_avg": 9.160896598495276, "review_time_days_median": 1.8337, "reviewers": 184, "submitted": 17600, "submitted_30": 1071, "submitted_365": 11846, "submitted_7": 255, "submitters": 103, "submitters_30": 59, "submitters_365": 91, "submitters_7": 38}