{"actions": 116745, "added_lines": 4754851.0, "added_lines_30": 123861, "added_lines_365": 2177992, "added_lines_7": 22676, "authors": 144, "authors_30": 69, "authors_365": 111, "authors_7": 49, "avg_commits_author": 168.8403, "avg_commits_month": 759.7813, "avg_files_author": 149.9028, "avg_files_month": 674.5625, "branches": 71, "commits": 24313, "commits_30": 991, "commits_365": 10851, "commits_7": 286, "committers": 108, "diff_netadded_lines_30": 6087, "diff_netadded_lines_365": 642824, "diff_netadded_lines_7": -23420, "diff_netauthors_30": -4, "diff_netauthors_365": 10, "diff_netauthors_7": -3, "diff_netcommits_30": 205, "diff_netcommits_365": 2476, "diff_netcommits_7": 2, "diff_netfiles_30": 325, "diff_netfiles_365": 5012, "diff_netfiles_7": -2, "diff_netremoved_lines_30": 16142, "diff_netremoved_lines_365": 341053, "diff_netremoved_lines_7": -16320, "files": 21586, "files_30": 2682, "files_365": 14210, "files_7": 1002, "first_date": "2011-11-01", "last_date": "2014-07-20", "percentage_added_lines_30": 5, "percentage_added_lines_365": 41, "percentage_added_lines_7": 50, "percentage_authors_30": 5, "percentage_authors_365": 9, "percentage_authors_7": 5, "percentage_commits_30": 26, "percentage_commits_365": 29, "percentage_commits_7": 0, "percentage_files_30": 13, "percentage_files_365": 54, "percentage_files_7": 0, "percentage_removed_lines_30": 37, "percentage_removed_lines_365": 30, "percentage_removed_lines_7": 69, "removed_lines": 3495489.0, "removed_lines_30": 59665, "removed_lines_365": 1441736, "removed_lines_7": 7237, "repositories": 35}