{"abandoned": 1713, "abandoned_30": 39, "abandoned_365": 1063, "abandoned_7": 3, "closed": 16521, "closed_30": 957, "closed_365": 11118, "closed_7": 178, "diff_netabandoned_30": -48, "diff_netabandoned_365": 500, "diff_netabandoned_7": -8, "diff_netclosed_30": -63, "diff_netclosed_365": 6751, "diff_netclosed_7": -72, "diff_netmerged_30": -15, "diff_netmerged_365": 6251, "diff_netmerged_7": -64, "diff_netpending_30": 153, "diff_netpending_365": 619, "diff_netpending_7": 26, "diff_netsubmitted_30": 90, "diff_netsubmitted_365": 7370, "diff_netsubmitted_7": -46, "diff_netsubmitters_30": -2, "diff_netsubmitters_365": 10, "diff_netsubmitters_7": -8, "first_date": "2011-10-26", "inprogress": 0, "last_date": "2014-09-13", "merged": 14808, "merged_30": 918, "merged_365": 10055, "merged_7": 175, "new": 511, "opened": 511, "pending": 651, "pending_30": 223, "pending_365": 634, "pending_7": 91, "percentage_abandoned_30": 55, "percentage_abandoned_365": 88, "percentage_abandoned_7": 72, "percentage_closed_30": 6, "percentage_closed_365": 154, "percentage_closed_7": 28, "percentage_merged_30": 1, "percentage_merged_365": 164, "percentage_merged_7": 26, "percentage_pending_30": 218, "percentage_pending_365": 4126, "percentage_pending_7": 40, "percentage_submitted_30": 8, "percentage_submitted_365": 168, "percentage_submitted_7": 14, "percentage_submitters_30": 3, "percentage_submitters_365": 12, "percentage_submitters_7": 15, "repositories": 34, "review_time_days_avg": 9.181578321678309, "review_time_days_median": 1.8874499999999999, "reviewers": 182, "submitted": 17172, "submitted_30": 1180, "submitted_365": 11752, "submitted_7": 269, "submitters": 103, "submitters_30": 62, "submitters_365": 91, "submitters_7": 45}