{"actions": 140805, "added_lines": 5462179.0, "added_lines_30": 32918, "added_lines_365": 1903289, "added_lines_7": 7768, "authors": 249, "authors_30": 69, "authors_365": 150, "authors_7": 32, "avg_commits_author": 121.43, "avg_commits_month": 795.71, "avg_files_author": 108.39, "avg_files_month": 710.26, "branches": 76, "commits": 30237, "commits_30": 506, "commits_365": 11209, "commits_7": 114, "committers": 249, "companies": 11, "core": 50, "diff_netadded_lines_30": -13174, "diff_netadded_lines_365": 181120, "diff_netadded_lines_7": 2171, "diff_netauthors_30": -5, "diff_netauthors_365": -3, "diff_netauthors_7": 9, "diff_netcommits_30": -293, "diff_netcommits_365": 1109, "diff_netcommits_7": 51, "diff_netfiles_30": -686, "diff_netfiles_365": 3919, "diff_netfiles_7": 67, "diff_netremoved_lines_30": -96112, "diff_netremoved_lines_365": -49889, "diff_netremoved_lines_7": -2624, "files": 26990, "files_30": 1203, "files_365": 15543, "files_7": 285, "first_date": "2011-11-01", "last_date": "2015-01-07", "occasional": 161, "percentage_added_lines_30": 28, "percentage_added_lines_365": 10, "percentage_added_lines_7": 38, "percentage_authors_30": 6, "percentage_authors_365": 1, "percentage_authors_7": 39, "percentage_commits_30": 36, "percentage_commits_365": 10, "percentage_commits_7": 80, "percentage_files_30": 36, "percentage_files_365": 33, "percentage_files_7": 30, "percentage_removed_lines_30": 86, "percentage_removed_lines_365": 3, "percentage_removed_lines_7": 50, "regular": 42, "removed_lines": 4039718.0, "removed_lines_30": 15148, "removed_lines_365": 1269366, "removed_lines_7": 2616, "repositories": 36, "type": "git", "url": "git://gerrit.ovirt.org/test"}