{"authors.":{"id":[82,30,10,8,42,54,63,55,58,31],"authors":["Allon Mureinik","Alon Bar-Lev","Michael Pasternak","Fabian Deutsch","Moti Asayag","Daniel Erez","Eli Mesika","Gilad Chaplik","Mike Kolesnik","Sandro Bonazzola"],"commits":[1225,1156,968,840,568,526,480,450,448,437]},"authors.last year":{"id":[30,82,31,8,10,110,106,42,104,54],"authors":["Alon Bar-Lev","Allon Mureinik","Sandro Bonazzola","Fabian Deutsch","Michael Pasternak","Lior Vernia","Alissa Bonas","Moti Asayag","Arik Hadas","Daniel Erez"],"commits":[949,644,436,401,383,300,271,252,230,224]},"authors.last month":{"id":[42,106,30,110,31,82,211,37,58,38],"authors":["Moti Asayag","Alissa Bonas","Alon Bar-Lev","Lior Vernia","Sandro Bonazzola","Allon Mureinik","Nir Soffer","Yaniv Dary","Mike Kolesnik","Alex Lourie"],"commits":[58,45,43,33,31,29,21,18,18,17]}}