{"actions": 121974, "added_lines": 4811554.0, "added_lines_30": 111032, "added_lines_365": 2164428, "added_lines_7": 10844, "authors": 228, "authors_30": 79, "authors_365": 153, "authors_7": 55, "avg_commits_author": 111.2763, "avg_commits_month": 792.8438, "avg_files_author": 99.0789, "avg_files_month": 705.9375, "branches": 71, "commits": 25371, "commits_30": 1057, "commits_365": 11335, "commits_7": 322, "committers": 139, "companies": 7, "core": 47, "diff_netadded_lines_30": -17979, "diff_netadded_lines_365": 622550, "diff_netadded_lines_7": -66876, "diff_netauthors_30": -4, "diff_netauthors_365": 9, "diff_netauthors_7": 3, "diff_netcommits_30": 160, "diff_netcommits_365": 2530, "diff_netcommits_7": 76, "diff_netfiles_30": -24, "diff_netfiles_365": 4320, "diff_netfiles_7": -31, "diff_netremoved_lines_30": 10078, "diff_netremoved_lines_365": 343072, "diff_netremoved_lines_7": -34033, "files": 22590, "files_30": 2626, "files_365": 14367, "files_7": 950, "first_date": "2011-11-01", "last_date": "2014-07-17", "occasional": 141, "percentage_added_lines_30": 13, "percentage_added_lines_365": 40, "percentage_added_lines_7": 86, "percentage_authors_30": 4, "percentage_authors_365": 6, "percentage_authors_7": 5, "percentage_commits_30": 17, "percentage_commits_365": 28, "percentage_commits_7": 30, "percentage_files_30": 0, "percentage_files_365": 42, "percentage_files_7": 3, "percentage_removed_lines_30": 20, "percentage_removed_lines_365": 31, "percentage_removed_lines_7": 83, "regular": 40, "removed_lines": 3515652.0, "removed_lines_30": 58898, "removed_lines_365": 1442523, "removed_lines_7": 6699, "repositories": 36, "type": "git", "url": "git://gerrit.ovirt.org/test"}