{"actions": 107348, "added_lines": 3965420.0, "added_lines_14": 137412.0, "added_lines_180": 1145397.0, "added_lines_30": 183395.0, "added_lines_365": 1947315.0, "added_lines_60": 381830.0, "added_lines_7": 35539.0, "added_lines_730": 3490139.0, "added_lines_90": 987584.0, "authors": 209, "authors_14": 53, "authors_180": 119, "authors_30": 74, "authors_365": 149, "authors_60": 93, "authors_7": 34, "authors_730": 199, "authors_90": 99, "avg_commits_author": 104.3158, "avg_commits_month": 778.6429, "avg_files_author": 95.4211, "avg_files_month": 712.25, "branches": 53, "commits": 21802, "commits_14": 427, "commits_180": 5841, "commits_30": 1078, "commits_365": 10926, "commits_60": 2452, "commits_7": 182, "commits_730": 19634, "commits_90": 3205, "committers": 129, "companies": 6, "companies_2006": 0, "companies_2009": 2, "companies_2012": 3, "core": 44, "diff_netadded_lines_30": -25450, "diff_netadded_lines_365": 394203, "diff_netadded_lines_7": -76613, "diff_netauthors_30": -8, "diff_netauthors_365": 6, "diff_netauthors_7": -15, "diff_netcommits_30": -303, "diff_netcommits_365": 2209, "diff_netcommits_7": -62, "diff_netfiles_30": -453, "diff_netfiles_365": 2659, "diff_netfiles_7": -77, "diff_netremoved_lines_30": -60559, "diff_netremoved_lines_365": 117692, "diff_netremoved_lines_7": -24609, "files": 19943, "files_14": 1826, "files_180": 9537, "files_30": 2887, "files_365": 13388, "files_60": 5297, "files_7": 997, "files_730": 18657, "files_90": 6822, "first_date": "2011-11-01", "last_date": "2014-03-16", "occasional": 126, "percentage_added_lines_30": 12, "percentage_added_lines_365": 25, "percentage_added_lines_7": 75, "percentage_authors_30": 9, "percentage_authors_365": 4, "percentage_authors_7": 30, "percentage_commits_30": 21, "percentage_commits_365": 25, "percentage_commits_7": 25, "percentage_files_30": 14, "percentage_files_365": 24, "percentage_files_7": 8, "percentage_removed_lines_30": 45, "percentage_removed_lines_365": 9, "percentage_removed_lines_7": 73, "regular": 39, "removed_lines": 2992594.0, "removed_lines_14": 52780.0, "removed_lines_180": 847065.0, "removed_lines_30": 83231.0, "removed_lines_365": 1400790.0, "removed_lines_60": 216621.0, "removed_lines_7": 19295.0, "removed_lines_730": 2673464.0, "removed_lines_90": 771989.0, "repositories": 36, "type": "git", "url": "git://gerrit.ovirt.org/test"}