{"authors.": {"authors": ["Alon Bar-Lev", "Allon Mureinik", "Fabian Deutsch", "Michael Pasternak", "Sandro Bonazzola", "Daniel Erez", "Juan Hernandez", "Moti Asayag", "Eli Mesika", "Gilad Chaplik"], "commits": [1697.0, 1376.0, 1189.0, 974.0, 913.0, 824.0, 730.0, 720.0, 632.0, 624.0], "id": [35, 97, 12, 13, 8, 72, 17, 54, 56, 73]}, "authors.last month": {"authors": ["Sandro Bonazzola", "Juan Hernandez", "Alon Bar-Lev", "pkliczewski", "Maor Lipchuk", "Ravi Nori", "Douglas Schilling Landgraf", "Tal Nisan", "Gilad Chaplik", "Simone Tiraboschi"], "commits": [66.0, 45.0, 43.0, 41.0, 38.0, 36.0, 33.0, 31.0, 30.0, 28.0], "id": [8, 17, 35, 159, 65, 21, 40, 85, 73, 38]}, "authors.last year": {"authors": ["Alon Bar-Lev", "Sandro Bonazzola", "Juan Hernandez", "Fabian Deutsch", "Lior Vernia", "Daniel Erez", "Allon Mureinik", "Yedidyah Bar David", "Ravi Nori", "Yair Zaslavsky"], "commits": [679.0, 593.0, 441.0, 393.0, 386.0, 348.0, 267.0, 261.0, 259.0, 252.0], "id": [35, 8, 17, 12, 124, 72, 97, 46, 21, 80]}}