{"authors.": {"authors": ["Alon Bar-Lev", "Allon Mureinik", "Fabian Deutsch", "Michael Pasternak", "Moti Asayag", "Daniel Erez", "Sandro Bonazzola", "Eli Mesika", "Gilad Chaplik", "Mike Kolesnik"], "commits": [1436, 1286, 1028, 973, 654, 605, 599, 526, 472, 468], "id": [30, 82, 8, 10, 42, 54, 31, 63, 55, 58]}, "authors.last month": {"authors": ["Alon Bar-Lev", "Sandro Bonazzola", "Juan Hernandez", "Yair Zaslavsky", "Fabian Deutsch", "Mooli Tayer", "Moti Asayag", "Allon Mureinik", "Ravi Nori", "Yedidyah Bar David"], "commits": [108, 77, 51, 45, 42, 41, 38, 33, 32, 32], "id": [30, 31, 14, 64, 8, 125, 42, 82, 18, 39]}, "authors.last year": {"authors": ["Alon Bar-Lev", "Sandro Bonazzola", "Allon Mureinik", "Fabian Deutsch", "Lior Vernia", "Moti Asayag", "Michael Pasternak", "Daniel Erez", "Arik Hadas", "Alissa Bonas"], "commits": [1054, 569, 509, 485, 351, 307, 280, 246, 242, 240], "id": [30, 31, 82, 8, 110, 42, 10, 54, 104, 106]}}