{"mergers.": {"id": [35, 12, 13, 8, 124, 43, 17, 54, 97, 72], "merged": [1295, 1022, 763, 751, 440, 394, 382, 342, 325, 323], "mergers": ["Alon Bar-Lev", "Fabian Deutsch", "Michael Pasternak", "Sandro Bonazzola", "Lior Vernia", "Yaniv Dary", "Juan Hernandez", "Moti Asayag", "Allon Mureinik", "Daniel Erez"]}, "mergers.last year": {"id": [35, 8, 124, 12, 17, 97, 72, 54, 118, 46], "merged": [879, 626, 375, 350, 347, 306, 305, 276, 244, 238], "mergers": ["Alon Bar-Lev", "Sandro Bonazzola", "Lior Vernia", "Fabian Deutsch", "Juan Hernandez", "Allon Mureinik", "Daniel Erez", "Moti Asayag", "Arik Hadas", "Yedidyah Bar David"]}, "mergers.last_month": {"id": [17, 8, 80, 35, 28, 91, 21, 12, 57, 124], "merged": [85, 68, 41, 35, 31, 30, 29, 28, 28, 28], "mergers": ["Juan Hernandez", "Sandro Bonazzola", "Yair Zaslavsky", "Alon Bar-Lev", "Dan Kenigsberg", "Alona Kaplan", "Ravi Nori", "Fabian Deutsch", "Shirly Radco", "Lior Vernia"]}, "openers.": {"id": [35, 12, 8, 13, 124, 17, 43, 54, 97, 72], "opened": [1350, 1143, 813, 782, 483, 478, 407, 366, 363, 333], "openers": ["Alon Bar-Lev", "Fabian Deutsch", "Sandro Bonazzola", "Michael Pasternak", "Lior Vernia", "Juan Hernandez", "Yaniv Dary", "Moti Asayag", "Allon Mureinik", "Daniel Erez"]}, "openers.last year": {"id": [35, 8, 124, 12, 17, 97, 72, 54, 118, 46], "opened": [923, 653, 415, 407, 398, 341, 312, 295, 292, 290], "openers": ["Alon Bar-Lev", "Sandro Bonazzola", "Lior Vernia", "Fabian Deutsch", "Juan Hernandez", "Allon Mureinik", "Daniel Erez", "Moti Asayag", "Arik Hadas", "Yedidyah Bar David"]}, "openers.last_month": {"id": [17, 8, 12, 80, 35, 97, 57, 21, 91, 124], "opened": [92, 68, 59, 42, 37, 37, 36, 35, 33, 33], "openers": ["Juan Hernandez", "Sandro Bonazzola", "Fabian Deutsch", "Yair Zaslavsky", "Alon Bar-Lev", "Allon Mureinik", "Shirly Radco", "Ravi Nori", "Alona Kaplan", "Lior Vernia"]}, "reviewers": {"id": [2641, 8, 28, 35, 97, 39, 12, 13, 80, 43], "reviewed": [11212, 7323, 7285, 5671, 5323, 5310, 4812, 4757, 4207, 4076], "reviewers": ["oVirt Jenkins CI Server", "Sandro Bonazzola", "Dan Kenigsberg", "Alon Bar-Lev", "Allon Mureinik", "Michael Burns", "Fabian Deutsch", "Michael Pasternak", "Yair Zaslavsky", "Yaniv Dary"]}, "reviewers.last month": {"id": [2641, 28, 37, 17, 8, 97, 80, 121, 114, 124], "reviewed": [855, 827, 680, 603, 490, 467, 412, 360, 342, 323], "reviewers": ["oVirt Jenkins CI Server", "Dan Kenigsberg", "Oved Ourfali", "Juan Hernandez", "Sandro Bonazzola", "Allon Mureinik", "Yair Zaslavsky", "awels", "Yaniv Bronhaim", "Lior Vernia"]}, "reviewers.last year": {"id": [2641, 28, 8, 97, 35, 1, 80, 17, 56, 87], "reviewed": [10214, 7188, 6356, 4915, 3760, 3612, 3579, 2995, 2910, 2876], "reviewers": ["oVirt Jenkins CI Server", "Dan Kenigsberg", "Sandro Bonazzola", "Allon Mureinik", "Alon Bar-Lev", "Itamar Heim", "Yair Zaslavsky", "Juan Hernandez", "Eli Mesika", "Omer Frenkel"]}}