{"WaitingForReviewer": 343, "WaitingForSubmitter": 400, "abandoned": 2222, "abandoned_30": 78, "abandoned_365": 1301, "abandoned_7": 19, "approved": 0, "closed": 18958, "closed_30": 889, "closed_365": 12353, "closed_7": 139, "codereview": 57965, "companies": 6, "diff_netabandoned_30": 17, "diff_netabandoned_365": 515, "diff_netabandoned_7": -5, "diff_netclosed_30": -262, "diff_netclosed_365": 6965, "diff_netclosed_7": -84, "diff_netmerged_30": -279, "diff_netmerged_365": 6450, "diff_netmerged_7": -79, "diff_netpending_30": 159, "diff_netpending_365": 777, "diff_netpending_7": 53, "diff_netsubmitted_30": -103, "diff_netsubmitted_365": 7742, "diff_netsubmitted_7": -31, "diff_netsubmitters_30": 0, "diff_netsubmitters_365": 25, "diff_netsubmitters_7": -1, "first_date": "2011-10-26", "inprogress": 0, "last_date": "2014-10-09", "merged": 16736, "merged_30": 811, "merged_365": 11052, "merged_7": 120, "new": 632, "opened": 632, "pending": 830, "pending_30": 280, "pending_365": 802, "pending_7": 114, "percentage_abandoned_30": 27, "percentage_abandoned_365": 65, "percentage_abandoned_7": 20, "percentage_closed_30": 22, "percentage_closed_365": 129, "percentage_closed_7": 37, "percentage_merged_30": 25, "percentage_merged_365": 140, "percentage_merged_7": 39, "percentage_pending_30": 131, "percentage_pending_365": 3108, "percentage_pending_7": 86, "percentage_submitted_30": 8, "percentage_submitted_365": 143, "percentage_submitted_7": 10, "percentage_submitters_30": 0, "percentage_submitters_365": 18, "percentage_submitters_7": 1, "repositories": 34, "review_time_days_avg": 10.518313907284734, "review_time_days_median": 1.9414, "reviewers": 249, "sent": 23372, "submitted": 19788, "submitted_30": 1169, "submitted_365": 13155, "submitted_7": 253, "submitters": 203, "submitters_30": 76, "submitters_365": 157, "submitters_7": 52, "verified": 46214}