{"mergers.": {"id": [12, 8, 13, 35, 28, 43, 19, 39, 17, 40], "merged": [1243, 856, 740, 717, 479, 405, 401, 393, 376, 368], "mergers": ["Fabian Deutsch", "Sandro Bonazzola", "Michael Pasternak", "Alon Bar-Lev", "Dan Kenigsberg", "Yaniv Dary", "Federico Simoncelli", "Michael Burns", "Juan Hernandez", "Douglas Schilling Landgraf"]}, "mergers.last year": {"id": [8, 12, 17, 57, 166, 35, 61, 40, 28, 41], "merged": [484, 368, 293, 245, 232, 219, 203, 184, 158, 154], "mergers": ["Sandro Bonazzola", "Fabian Deutsch", "Juan Hernandez", "Shirly Radco", "Francesco Romani", "Alon Bar-Lev", "Nir Soffer", "Douglas Schilling Landgraf", "Dan Kenigsberg", "Ryan Barry"]}, "mergers.last_month": {"id": [12, 39874, 8, 40226, 17, 46, 61, 35, 166, 86], "merged": [52, 33, 26, 22, 21, 19, 19, 18, 17, 15], "mergers": ["Fabian Deutsch", "mlipchuk", "Sandro Bonazzola", "ahadas", "Juan Hernandez", "Yedidyah Bar David", "Nir Soffer", "Alon Bar-Lev", "Francesco Romani", "Tomas Jelinek"]}, "openers.": {"id": [12, 8, 13, 35, 28, 19, 40, 39, 43, 166], "opened": [1372, 917, 755, 743, 532, 518, 452, 437, 419, 409], "openers": ["Fabian Deutsch", "Sandro Bonazzola", "Michael Pasternak", "Alon Bar-Lev", "Dan Kenigsberg", "Federico Simoncelli", "Douglas Schilling Landgraf", "Michael Burns", "Yaniv Dary", "Francesco Romani"]}, "openers.last year": {"id": [8, 12, 166, 17, 61, 57, 35, 40, 41, 28], "opened": [508, 413, 378, 316, 287, 263, 225, 223, 197, 180], "openers": ["Sandro Bonazzola", "Fabian Deutsch", "Francesco Romani", "Juan Hernandez", "Nir Soffer", "Shirly Radco", "Alon Bar-Lev", "Douglas Schilling Landgraf", "Ryan Barry", "Dan Kenigsberg"]}, "openers.last_month": {"id": [12, 166, 39874, 61, 40226, 8, 46, 124, 170, 17], "opened": [53, 44, 40, 35, 27, 26, 25, 25, 25, 22], "openers": ["Fabian Deutsch", "Francesco Romani", "mlipchuk", "Nir Soffer", "ahadas", "Sandro Bonazzola", "Yedidyah Bar David", "Lior Vernia", "Martin Mucha", "Juan Hernandez"]}, "reviewers": {"id": [28, 12, 42063, 39, 8, 114, 35, 43, 19, 166], "reviewed": [29522, 14366, 11091, 9504, 9406, 6690, 6149, 6135, 6081, 6010], "reviewers": ["Dan Kenigsberg", "Fabian Deutsch", "jenkins", "Michael Burns", "Sandro Bonazzola", "Yaniv Bronhaim", "Alon Bar-Lev", "Yaniv Dary", "Federico Simoncelli", "Francesco Romani"]}, "reviewers.last month": {"id": [42063, 28, 166, 39874, 85, 12, 40226, 8, 61, 124], "reviewed": [1149, 1010, 540, 527, 469, 453, 444, 422, 357, 350], "reviewers": ["jenkins", "Dan Kenigsberg", "Francesco Romani", "mlipchuk", "Tal Nisan", "Fabian Deutsch", "ahadas", "Sandro Bonazzola", "Nir Soffer", "Lior Vernia"]}, "reviewers.last year": {"id": [28, 42063, 166, 8, 12, 114, 61, 17, 43, 57], "reviewed": [11140, 6784, 5711, 5145, 4881, 3831, 3176, 3148, 2836, 2710], "reviewers": ["Dan Kenigsberg", "jenkins", "Francesco Romani", "Sandro Bonazzola", "Fabian Deutsch", "Yaniv Bronhaim", "Nir Soffer", "Juan Hernandez", "Yaniv Dary", "Shirly Radco"]}}