{"mergers.": {"id": [30, 8, 10, 31, 37, 110, 34, 42, 82, 161], "merged": [1097, 892, 763, 536, 337, 307, 285, 273, 256, 256], "mergers": ["Alon Bar-Lev", "Fabian Deutsch", "Michael Pasternak", "Sandro Bonazzola", "Yaniv Dary", "Lior Vernia", "Mike Burns", "Moti Asayag", "Allon Mureinik", "Joey Boggs"]}, "mergers.last year": {"id": [30, 31, 8, 110, 42, 82, 10, 106, 14, 104], "merged": [941, 527, 419, 306, 272, 256, 244, 198, 194, 180], "mergers": ["Alon Bar-Lev", "Sandro Bonazzola", "Fabian Deutsch", "Lior Vernia", "Moti Asayag", "Allon Mureinik", "Michael Pasternak", "Alissa Bonas", "Juan Hernandez", "Arik Hadas"]}, "mergers.last_month": {"id": [30, 31, 14, 8, 42, 64, 119, 69, 41, 37], "merged": [135, 72, 54, 51, 36, 36, 33, 32, 29, 27], "mergers": ["Alon Bar-Lev", "Sandro Bonazzola", "Juan Hernandez", "Fabian Deutsch", "Moti Asayag", "Yair Zaslavsky", "Martin Perina", "Tal Nisan", "Martin Sivak", "Yaniv Dary"]}, "openers.": {"id": [30, 8, 10, 31, 37, 110, 34, 42, 14, 161], "opened": [1148, 987, 782, 586, 347, 332, 301, 292, 281, 275], "openers": ["Alon Bar-Lev", "Fabian Deutsch", "Michael Pasternak", "Sandro Bonazzola", "Yaniv Dary", "Lior Vernia", "Mike Burns", "Moti Asayag", "Juan Hernandez", "Joey Boggs"]}, "openers.last year": {"id": [30, 31, 8, 110, 42, 82, 14, 10, 106, 104], "opened": [990, 577, 475, 331, 291, 270, 263, 255, 216, 207], "openers": ["Alon Bar-Lev", "Sandro Bonazzola", "Fabian Deutsch", "Lior Vernia", "Moti Asayag", "Allon Mureinik", "Juan Hernandez", "Michael Pasternak", "Alissa Bonas", "Arik Hadas"]}, "openers.last_month": {"id": [30, 31, 8, 14, 64, 42, 119, 1807, 69, 41], "opened": [160, 79, 65, 59, 46, 39, 38, 36, 35, 33], "openers": ["Alon Bar-Lev", "Sandro Bonazzola", "Fabian Deutsch", "Juan Hernandez", "Yair Zaslavsky", "Moti Asayag", "Martin Perina", "Shirly Radco", "Tal Nisan", "Martin Sivak"]}, "reviewers": {"id": [1569, 34, 31, 10, 30, 82, 8, 26, 37, 1], "reviewed": [5414, 5310, 5201, 4716, 4359, 3791, 3745, 3650, 2888, 2876], "reviewers": ["oVirt Jenkins CI Server", "Mike Burns", "Sandro Bonazzola", "Michael Pasternak", "Alon Bar-Lev", "Allon Mureinik", "Fabian Deutsch", "Dan Kenigsberg", "Yaniv Dary", "Itamar Heim"]}, "reviewers.last month": {"id": [31, 30, 63, 26, 1569, 64, 14, 1, 37, 54], "reviewed": [786, 665, 648, 621, 608, 527, 459, 412, 402, 286], "reviewers": ["Sandro Bonazzola", "Alon Bar-Lev", "Eli Mesika", "Dan Kenigsberg", "oVirt Jenkins CI Server", "Yair Zaslavsky", "Juan Hernandez", "Itamar Heim", "Yaniv Dary", "Daniel Erez"]}, "reviewers.last year": {"id": [1569, 31, 82, 30, 26, 1, 8, 64, 63, 42], "reviewed": [5284, 5168, 3779, 3595, 3588, 2833, 2708, 2352, 2311, 2093], "reviewers": ["oVirt Jenkins CI Server", "Sandro Bonazzola", "Allon Mureinik", "Alon Bar-Lev", "Dan Kenigsberg", "Itamar Heim", "Fabian Deutsch", "Yair Zaslavsky", "Eli Mesika", "Moti Asayag"]}}