{"mergers.": {"id": [35, 12, 8, 13, 124, 17, 72, 43, 97, 54], "merged": [1430, 1104, 959, 763, 515, 505, 423, 410, 369, 354], "mergers": ["Alon Bar-Lev", "Fabian Deutsch", "Sandro Bonazzola", "Michael Pasternak", "Lior Vernia", "Juan Hernandez", "Daniel Erez", "Yaniv Dary", "Allon Mureinik", "Moti Asayag"]}, "mergers.last year": {"id": [35, 8, 17, 72, 124, 12, 97, 39743, 40226, 42], "merged": [675, 641, 441, 342, 309, 295, 261, 251, 244, 238], "mergers": ["Alon Bar-Lev", "Sandro Bonazzola", "Juan Hernandez", "Daniel Erez", "Lior Vernia", "Fabian Deutsch", "Allon Mureinik", "yzaslavs", "ahadas", "Martin Perina"]}, "mergers.last_month": {"id": [8, 12, 35, 159, 17, 72, 9, 46, 57, 114], "merged": [53, 27, 27, 23, 22, 19, 18, 17, 16, 16], "mergers": ["Sandro Bonazzola", "Fabian Deutsch", "Alon Bar-Lev", "pkliczewski", "Juan Hernandez", "Daniel Erez", "David Caro", "Yedidyah Bar David", "Shirly Radco", "Yaniv Bronhaim"]}, "openers.": {"id": [35, 12, 8, 13, 17, 124, 72, 43, 40226, 54], "opened": [1500, 1225, 1037, 782, 619, 567, 432, 426, 422, 411], "openers": ["Alon Bar-Lev", "Fabian Deutsch", "Sandro Bonazzola", "Michael Pasternak", "Juan Hernandez", "Lior Vernia", "Daniel Erez", "Yaniv Dary", "ahadas", "Moti Asayag"]}, "openers.last year": {"id": [35, 8, 17, 124, 166, 72, 12, 39743, 40226, 61], "opened": [727, 681, 497, 354, 349, 348, 343, 315, 309, 288], "openers": ["Alon Bar-Lev", "Sandro Bonazzola", "Juan Hernandez", "Lior Vernia", "Francesco Romani", "Daniel Erez", "Fabian Deutsch", "yzaslavs", "ahadas", "Nir Soffer"]}, "openers.last_month": {"id": [8, 166, 35, 41, 159, 12, 17, 40226, 114, 61], "opened": [61, 47, 39, 38, 30, 29, 28, 28, 27, 26], "openers": ["Sandro Bonazzola", "Francesco Romani", "Alon Bar-Lev", "Ryan Barry", "pkliczewski", "Fabian Deutsch", "Juan Hernandez", "ahadas", "Yaniv Bronhaim", "Nir Soffer"]}, "reviewers": {"id": [42063, 28, 8, 35, 97, 12, 39743, 39, 17, 85], "reviewed": [14243, 10152, 9502, 6862, 6766, 5993, 5598, 5310, 4953, 4858], "reviewers": ["jenkins", "Dan Kenigsberg", "Sandro Bonazzola", "Alon Bar-Lev", "Allon Mureinik", "Fabian Deutsch", "yzaslavs", "Michael Burns", "Juan Hernandez", "Tal Nisan"]}, "reviewers.last month": {"id": [167, 42063, 28, 85, 8, 166, 114, 87, 17, 37], "reviewed": [996, 968, 776, 766, 617, 541, 487, 439, 435, 424], "reviewers": ["Yevgeny Zaspitsky", "jenkins", "Dan Kenigsberg", "Tal Nisan", "Sandro Bonazzola", "Francesco Romani", "Yaniv Bronhaim", "Omer Frenkel", "Juan Hernandez", "Oved Ourfali"]}, "reviewers.last year": {"id": [42063, 28, 8, 97, 17, 37, 85, 39743, 35, 114], "reviewed": [12020, 9063, 6756, 4660, 4504, 4381, 4249, 4244, 3873, 3429], "reviewers": ["jenkins", "Dan Kenigsberg", "Sandro Bonazzola", "Allon Mureinik", "Juan Hernandez", "Oved Ourfali", "Tal Nisan", "yzaslavs", "Alon Bar-Lev", "Yaniv Bronhaim"]}}