{"actions": 9307, "added_lines": 203205.0, "added_lines_30": 41612, "added_lines_365": 2443159, "added_lines_7": 7043, "authors": 130, "authors_30": 23, "authors_365": 79, "authors_7": 13, "avg_commits_author": 31.4077, "avg_commits_month": 116.6571, "avg_files_author": 8.3769, "avg_files_month": 31.1143, "branches": 7, "commits": 4083, "commits_30": 151, "commits_365": 1751, "commits_7": 47, "committers": 6, "diff_netadded_lines_30": -304597, "diff_netadded_lines_365": 826535, "diff_netadded_lines_7": 803, "diff_netauthors_30": 0, "diff_netauthors_365": 7, "diff_netauthors_7": 0, "diff_netcommits_30": -41, "diff_netcommits_365": 631, "diff_netcommits_7": 23, "diff_netfiles_30": -8, "diff_netfiles_365": 171, "diff_netfiles_7": -6, "diff_netremoved_lines_30": -278263, "diff_netremoved_lines_365": 587026, "diff_netremoved_lines_7": -1169, "files": 1089, "files_30": 165, "files_365": 707, "files_7": 68, "first_date": "2011-11-01", "last_date": "2014-10-25", "percentage_added_lines_30": 87, "percentage_added_lines_365": 51, "percentage_added_lines_7": 12, "percentage_authors_30": 0, "percentage_authors_365": 9, "percentage_authors_7": 0, "percentage_commits_30": 21, "percentage_commits_365": 56, "percentage_commits_7": 95, "percentage_files_30": 4, "percentage_files_365": 31, "percentage_files_7": 8, "percentage_removed_lines_30": 92, "percentage_removed_lines_365": 51, "percentage_removed_lines_7": 23, "removed_lines": 117118.0, "removed_lines_30": 21227, "removed_lines_365": 1717346, "removed_lines_7": 3861, "repositories": 1}