{"authors.": {"authors": ["Dan Kenigsberg", "Federico Simoncelli", "Antoni S. Puimedon", "Nir Soffer", "Francesco Romani", "Saggi Mizrahi", "Yaniv Bronhaim", "Douglas Schilling Landgraf", "Eduardo Warszawski", "Adam Litke"], "commits": [454, 390, 286, 273, 255, 225, 213, 210, 173, 149], "id": [28, 19, 11, 61, 166, 107, 114, 40, 188, 16]}, "authors.last month": {"authors": ["Nir Soffer", "Francesco Romani", "Dan Kenigsberg", "Ond\u0159ej Svoboda", "mpolednik", "Petr Hor\u00e1\u010dek", "darshan n", "y kaplan", "Amador Pahim", "Mooli Tayer"], "commits": [29, 27, 19, 17, 10, 8, 7, 7, 6, 5], "id": [61, 166, 28, 252, 153, 7776, 68, 204, 33, 138]}, "authors.last year": {"authors": ["Francesco Romani", "Nir Soffer", "Dan Kenigsberg", "Antoni S. Puimedon", "pkliczewski", "Federico Simoncelli", "Yaniv Bronhaim", "Ond\u0159ej Svoboda", "Adam Litke", "Mooli Tayer"], "commits": [237, 229, 151, 138, 117, 99, 81, 65, 64, 62], "id": [166, 61, 28, 11, 159, 19, 114, 252, 16, 138]}}